{
   "id" : "castDef_theDaughter",
   "internalName" : "theDaughter",
   "firstName" : "Eleonore",
   "lastName" : "Rothall",
   "callsign" : "Badger",
   "rank" : "Froness Hieress",
   "gender" : "Female",
   "factionID" : "faction_froness",
   "sgCharType" : "UNSET",
   "showRank" : true,
   "showFirstName" : true,
   "showCallsign" : false,
   "showLastName" : true,
   "localizeName" : false,
   "defaultEmotePortrait" : {
      "emote" : "Default",
      "portraitAssetPath" : "../../mods/XAI Flashpoints/Flashpoint - The Baron Wars/sprites/Portraits/guiTxrPort_theDaughter.png"
   },
   "emotePotraitList" : [
      
   ]
}
