{
	"Description": {
		"Id": "lancedef_Irukjandi_Battle",
		"Name": "Dynamic Irukjandi Battle",
		"Details": "Irukjandi Battle",
		"Icon": "uixTxrIcon_Irukjandi",
		"Cost": 0,
		"Rarity": 0,
		"Purchasable": false
	},
	"Difficulty": 4,
	"LanceTags": {
		"items": [
			
			"lance_type_medium",
			"lance_type_dynamic",
			"lance_type_mech",
			"lance_type_notallvehicles"
		],
		"tagSetSourceFile": "Tags/LanceTags"
	},
	"LanceUnits": [
		{
			"unitType": "Mech",
			"unitId": "Tagged",
			"pilotId": "pilot_Ico5_gunner",
			"unitTagSet": {
				"items": [ "unit_mech", "unit_range_long" , "unit_medium"],
				"tagSetSourceFile": "Tags/UnitTags"
			},
			"excludedUnitTagSet": {
				"items": [ "unit_type_vehicle","unit_noncombatant", "unit_speed_low" ],
				"tagSetSourceFile": "Tags/UnitTags"
			},
			"pilotTagSet": {
				"items": [],
				"tagSetSourceFile": "Tags/PilotTags"
			},
			"excludedPilotTagSet": {
				"items": null,
				"tagSetSourceFile": "Tags/PilotTags"
			}
		},
		{
			"unitType": "Mech",
			"unitId": "Tagged",
			"pilotId": "pilot_Ico5_gunner",
			"unitTagSet": {
				"items": [ "unit_mech", "unit_medium", "unit_speed_high"],
				"tagSetSourceFile": "Tags/UnitTags"
			},
			"excludedUnitTagSet": {
				"items": [ "unit_type_vehicle","unit_noncombatant", "unit_speed_low" ],
				"tagSetSourceFile": "Tags/UnitTags"
			},
			"pilotTagSet": {
				"items": [],
				"tagSetSourceFile": "Tags/PilotTags"
			},
			"excludedPilotTagSet": {
				"items": null,
				"tagSetSourceFile": "Tags/PilotTags"
			}
		},
		{
			"unitType": "Mech",
			"unitId": "Tagged",
			"pilotId": "pilot_Ico5_gunner",
			"unitTagSet": {
				"items": [ "unit_mech", "unit_heavy" , "unit_speed_high"  ],
				"tagSetSourceFile": "Tags/UnitTags"
			},
			"excludedUnitTagSet": {
				"items": [

					"unit_noncombatant",
					"unit_speed_low"
				],
				"tagSetSourceFile": "Tags/UnitTags"
			},
			"pilotTagSet": {
				"items": [],
				"tagSetSourceFile": "Tags/PilotTags"
			},
			"excludedPilotTagSet": {
				"items": null,
				"tagSetSourceFile": "Tags/PilotTags"
			}
		},
		{
			"unitType": "Mech",
			"unitId": "Tagged",
			"pilotId": "pilot_Ico5_gunner",
			"unitTagSet": {
				"items": [ "unit_mech", "unit_lance_support" , "unit_light"],
				"tagSetSourceFile": "Tags/UnitTags"
			},
			"excludedUnitTagSet": {
				"items": [ "unit_vehicle", "unit_lance_tank", "unit_noncombatant" ,"unit_speed_low"],
				"tagSetSourceFile": "Tags/UnitTags"
			},
			"pilotTagSet": {
				"items": [],
				"tagSetSourceFile": "Tags/PilotTags"
			},
			"excludedPilotTagSet": {
				"items": null,
				"tagSetSourceFile": "Tags/PilotTags"
			}
		}
	]
}