{
	"Description": {
		"Id": "lancedef_Irukjandi_Scout",
		"Name": "Dynamic Irukjandi Scout",
		"Details": "Irukjandi Scout",
		"Icon": "uixTxrIcon_Irukjandi",
		"Cost": 0,
		"Rarity": 0,
		"Purchasable": false
	},
	"Difficulty": 4,
	"LanceTags": {
		"items": [
			"lance_bracket_low",
			"lance_type_medium",
			"lance_type_dynamic",
			"lance_type_mech",
			"lance_type_notallvehicles"
		],
		"tagSetSourceFile": "Tags/LanceTags"
	},
	"LanceUnits": [
		{
			"unitType": "Mech",
			"unitId": "Tagged",
			"pilotId": "pilot_Ico5_gunner",
			"unitTagSet": {
				"items": [ "unit_mech", "unit_range_long", "unit_medium", ],
				"tagSetSourceFile": "Tags/UnitTags"
			},
			"excludedUnitTagSet": {
				"items": [],
				"tagSetSourceFile": "Tags/UnitTags"
			},
			"pilotTagSet": {
				"items": [],
				"tagSetSourceFile": "Tags/PilotTags"
			},
			"excludedPilotTagSet": {
				"items": null,
				"tagSetSourceFile": "Tags/PilotTags"
			}
		},
		{
			"unitType": "Mech",
			"unitId": "Tagged",
			"pilotId": "pilot_Ico5_tactician",
			"unitTagSet": {
				"items": [ "unit_medium", "unit_speed_high" ],
				"tagSetSourceFile": "Tags/UnitTags"
			},
			"excludedUnitTagSet": {
				"items": [],
				"tagSetSourceFile": "Tags/UnitTags"
			},
			"pilotTagSet": {
				"items": [],
				"tagSetSourceFile": "Tags/PilotTags"
			},
			"excludedPilotTagSet": {
				"items": null,
				"tagSetSourceFile": "Tags/PilotTags"
			}
		},
		{
			"unitType": "Mech",
			"unitId": "Tagged",
			"pilotId": "pilot_Ico5_gunner",
			"unitTagSet": {
				"items": [ "unit_light" ],
				"tagSetSourceFile": "Tags/UnitTags"
			},
			"excludedUnitTagSet": {
				"items": [],
				"tagSetSourceFile": "Tags/UnitTags"
			},
			"pilotTagSet": {
				"items": [],
				"tagSetSourceFile": "Tags/PilotTags"
			},
			"excludedPilotTagSet": {
				"items": null,
				"tagSetSourceFile": "Tags/PilotTags"
			}
		},
		{
			"unitType": "Mech",
			"unitId": "Tagged",
			"pilotId": "pilot_Ico5_gunner",
			"unitTagSet": {
				"items": [ "unit_lance_support" , "unit_light"],
				"tagSetSourceFile": "Tags/UnitTags"
			},
			"excludedUnitTagSet": {
				"items": [],
				"tagSetSourceFile": "Tags/UnitTags"
			},
			"pilotTagSet": {
				"items": [],
				"tagSetSourceFile": "Tags/PilotTags"
			},
			"excludedPilotTagSet": {
				"items": null,
				"tagSetSourceFile": "Tags/PilotTags"
			}
		}
	]
}