{
  "ID": "c_fp_TBW_AmbushRathbottom_f",
  "RandomSpawns": {"Enable": true},
  "HotDropProtection": {
    "Enable": true
  },
  "AdditionalLances": {
    "Enable": true,
    "EnemyLanceCount": 1,
    "EnemyLanceObjectiveNames": ["Destroy Additional enemy Lance."],
    "EnemyLances": ["lancedef_mech_d6_dynamic_MedHeavyCavalry"],
    "UseDialogue": true,
    "DialogueCastDefId": "castDef_theBaron_pilot",
    "Dialogue": "Sorry {Commander.LastName}, I've only just go my Comms on-line. I just couldn't make it on time... Please, just get the Governor.",
    "AllyLanceCount": 0,
    "AllyLances": []
  },
  "ExtendedLances": {
    "Enable": false,
    "EnemyLanceSize": 4,
    "AllyLanceSize": 4
  },
  "ExtendedBoundaries": {
    "Enable": true,
    "IncreaseBoundarySizeByPercentage": 0.5
  },
  "DynamicWithdraw": {
    "Enable": true
  },
  "AdditionalPlayerMechs": {
    "Enable": false
  }
}
